Workbook

Sheet Read Me
B1: Rockland & Hanover Drop-Off Target List
B2: In-person prospecting universe for 5 Point Technology. Built August 24, 2026.
B4: What this is
B5: 104 businesses within about 15 minutes of Rockland and Hanover, MA: Rockland, Hanover, Norwell,
B6: Pembroke, Whitman, Abington, Hanson, plus one flagged nearby HQ. Sized roughly 20 to 500 on site,
B7: with a few larger local anchors kept in on purpose. Grouped into drivable half-day routes.
B9: Tiers
B10: A | C10: Bullseye. Fits the 5PT ICP: 50 to 500 staff or a compliance heavy vertical, decision maker on site.
B11: B | C11: Strong fit. Typically 25 to 100 staff, real office and operations, worth a stop on every route pass.
B12: C | C12: Opportunistic. Branches of larger companies, big local anchors, trades and dealers. Visit when on route.
B14: Counts
B15: Total targets | C15: =COUNTA('Target List'!$C$2:$C$105) -> 104
B16: Tier A | C16: =COUNTIF('Target List'!$A$2:$A$105,"A") -> 29
B17: Tier B | C17: =COUNTIF('Target List'!$A$2:$A$105,"B") -> 45
B18: Tier C | C18: =COUNTIF('Target List'!$A$2:$A$105,"C") -> 30
B19: With named IT contact | C19: =COUNTIF('Target List'!$H$2:$H$105,"?*") -> 36
B20: With named owner/exec | C20: =COUNTIF('Target List'!$I$2:$I$105,"?*") -> 77
B22: Your columns (highlighted yellow in the Target List)
B23: Status, Visit date, and Next step are yours to fill after each stop. Status has a dropdown. Example:
C24: Status | D24: Visit date | E24: Next step
C25: Met DM | D25: 09/03/26 | E25: Call booked Tue 9/9 9am w/ Anthony
B27: Sources and caveats
B28: Company and contact data: ZoomInfo, pulled and enriched 08/24/2026. Flagged rows spot checked on the web.
B29: Employee counts are ZoomInfo estimates and often span all of a company's locations, not just this address.
B30: Excluded on purpose: town government, public schools, police, restaurants and salons, other IT providers,
B31: and listings that were defunct or wrongly geocoded. Contact names age fast: confirm at the front desk.
B32: The Parent / ownership column flags branches and acquisitions where IT may be decided elsewhere.

Sheet Target List
A1: Tier | B1: Route | C1: Company | D1: What they do | E1: Street (map link) | F1: Town | G1: Phone | H1: IT contact (ask for) | I1: Owner / exec | J1: Door opener | K1: Emp est | L1: Rev $M | M1: Founded | N1: Parent / ownership | O1: Website | P1: Notes | Q1: Status | R1: Visit date | S1: Next step | T1: ZIP | U1: ZoomInfo ID
A2: A | B2: R1 Rockland Exit14/Ledgewood | C2: Cutter Associates | D2: Investment management research and consulting | E2: 1050 Hingham St, Fl 1 | F2: Rockland | G2: (339) 469-0600 | I2: Cindy Castellano (Chief Executive Officer) | J2: Financial services firm handling asset manager data. Lead with security posture and M365 hardening. | K2: 97 | L2: 26372000 | M2: 1998 | N2: Nomura Research Institute | O2: cutterassociates.com | P2: Owned by Nomura Research Institute since 2022. Local office still runs day to day here. Hybrid workforce. | Q2: Not visited | T2: 02370 | U2: 19993081
A3: A | B3: R1 Rockland Exit14/Ledgewood | C3: FINTRX | D3: Family office and RIA data platform (SaaS) | E3: 40 Reservoir Park Dr, Ste A | F3: Rockland | G3: (617) 517-0789 | H3: Bruno Bonifacini (Software Developer & Security Integrations Specialist) | I3: Dennis Caulfield (Chief Product & Data Officer) | J3: Growing fintech with SOC 2 expectations from clients. Lead with co-managed security and compliance. | K3: 85 | L3: 17855000 | M3: 2014 | O3: fintrx.com | P3: Has developers but likely thin IT ops. Good co-managed fit. Fast growth company. | Q3: Not visited | T3: 02370 | U3: 461888001
A4: B | B4: R1 Rockland Exit14/Ledgewood | C4: The Catered Affair | D4: High end catering and events company, HQ | E4: 70 Ledgewood Pl | F4: Rockland | G4: (781) 982-9333 | H4: Gare Reid (Manager, Systems Integration) | I4: Holly Safford (Founder & President) | J4: Seasonal staff surges and POS plus office systems. Lead with device turnaround and help desk overflow. | K4: 320 | L4: 58320000 | M4: 1980 | O4: thecateredaffair.com | P4: Runs venues across Boston area from this HQ. Employee count includes event staff. | Q4: Not visited | T4: 02370 | U4: 7012563
A5: B | B5: R1 Rockland Exit14/Ledgewood | C5: ControlPoint Technologies | D5: Electrical engineering and utility consulting | E5: 200 Ledgewood Pl, Ste 300 | F5: Rockland | G5: (781) 261-9666 | H5: Adam Houghton (Director, System Planning) | I5: Jeffrey Flint (President) | J5: Engineers with CAD workstations and utility client data. Lead with backup, DR and project file uptime. | K5: 74 | L5: 9809000 | M5: 1999 | O5: cpteng.com | P5: Same building as Food Tech. Two stops, one parking lot. | Q5: Not visited | T5: 02370 | U5: 9470939
A6: B | B6: R1 Rockland Exit14/Ledgewood | C6: Burke & Associates CPAs | D6: CPA and advisory firm | E6: 300 Ledgewood Pl, Ste 300 | F6: Rockland | G6: (781) 741-8887 | J6: CPA firms must have a written security plan under FTC Safeguards. Ask who maintains their WISP. | K6: 27 | L6: 5377000 | M6: 1997 | O6: burkeandassoc.com | P6: Tax season uptime is everything. Best visited May through November. | Q6: Not visited | T6: 02370 | U6: 44551959
A7: C | B7: R1 Rockland Exit14/Ledgewood | C7: EMD Serono | D7: Biopharma R&D campus (Merck KGaA) | E7: 1 Technology Pl | F7: Rockland | G7: (800) 283-8088 | H7: Richard Feldman (Vice President, Trade Product Security & Done) | J7: Enterprise IT runs from global. Networking value only. Do not cold walk in past security. | K7: 2105 | L7: 758493000 | M7: 1981 | N7: Merck KGaA | O7: emdserono.com | P7: Long shot. Better reached through events or referrals than a lobby visit. | Q7: Not visited | T7: 02370 | U7: 92047565
A8: C | B8: R1 Rockland Exit14/Ledgewood | C8: Food Tech | D8: Design build firm for food processing facilities | E8: 200 Ledgewood Pl, Ste 200 | F8: Rockland | G8: (781) 261-9700 | H8: Leanda Karunia (Manager, Process & System Cum PA) | I8: Jonathan Kohan (President) | J8: Project teams in the field need reliable laptops and file access. Lead with device management. | K8: 40 | L8: 3149000 | M8: 2008 | N8: EMCOR Group | O8: foodtech.com | P8: EMCOR subsidiary, so corporate IT may exist. Local office worth a walk in while next door. | Q8: Not visited | T8: 02370 | U8: 27002672
A9: A | B9: R2 Rockland Weymouth/Union | C9: Rockland Federal Credit Union | D9: Credit union, main office | E9: 241 Union St | F9: Rockland | G9: (781) 878-0232 | H9: Mark Federico (Chief Information Officer) | I9: Kristin VanBeek (Chief Executive Officer & President) | J9: NCUA exams and vendor management pressure. Lead with vCISO, compliance alignment and MDR. | K9: 297 | L9: 73741000 | M9: 1922 | O9: rfcu.com | P9: Has internal IT led by a senior VP. Co-managed and security services angle, not full outsource. | Q9: Not visited | T9: 02370 | U9: 59785848
A10: A | B10: R2 Rockland Weymouth/Union | C10: UPPAbaby | D10: Premium stroller and car seat brand, global HQ | E10: 276 Weymouth St | F10: Rockland | G10: (781) 413-3000 | H10: Darrell Van Meter (Director, Information Technology) | I10: Bob Monahan (Chief Executive Officer & Co-Founder) | J10: Consumer brand with e-commerce, EDI and product data to protect. Lead with security and uptime. | K10: 136 | L10: 21613000 | M10: 2006 | O10: uppababy.com | P10: Flagship local HQ. CPSC regulated products mean documentation and systems matter. | Q10: Not visited | T10: 02370 | U10: 353910475
A11: A | B11: R2 Rockland Weymouth/Union | C11: Polymer Corporation | D11: Custom plastics and thermoforming manufacturer | E11: 180 Pleasant St | F11: Rockland | G11: (781) 871-4606 | H11: Ashwani Sharma (System Engineer) | I11: Jim Ryan (President) | J11: 100 person manufacturer, likely 0 to 2 IT staff. Lead with co-managed support and plant uptime. | K11: 103 | L11: 26997000 | M11: 1979 | O11: polymercorporation.com | P11: Classic ICP manufacturer. Strong first stop. | Q11: Not visited | T11: 02370 | U11: 343688307
A12: A | B12: R2 Rockland Weymouth/Union | C12: Briggs Engineering | D12: Civil and structural engineering, survey | E12: 100 Weymouth St, Ste C2 | F12: Rockland | G12: (781) 871-6040 | I12: Sean Skorohod (Testing Services President & Director) | J12: CAD and survey data with municipal clients. Lead with backup, DR and file server performance. | K12: 80 | L12: 30145000 | M12: 1958 | O12: briggsengineering.com | P12: Same complex as Bendon Gear. Two stops, one lot. | Q12: Not visited | T12: 02370 | U12: 17159799
A13: A | B13: R2 Rockland Weymouth/Union | C13: National Coating | D13: Coated fabrics and technical textiles manufacturer | E13: 105 Industrial Way | F13: Rockland | G13: (800) 979-9332 | J13: Production scheduling and quality systems on aging infrastructure is common here. Ask about uptime. | K13: 48 | L13: 13780000 | M13: 1977 | O13: natcoat.com | Q13: Not visited | T13: 02370 | U13: 353777346
A14: B | B14: R2 Rockland Weymouth/Union | C14: K5 Corporation | D14: Utility and civil construction contractor | E14: 9 Rockview Way, Ste B | F14: Rockland | G14: (781) 982-9229 | I14: Ronald Beaudoin (Chief Executive Officer) | J14: Contractors are prime wire fraud targets. Lead with email security and payment fraud protection. | K14: 104 | L14: 24829000 | M14: 1982 | O14: k5corporation.com | P14: Next door to Commonwealth Building Systems. | Q14: Not visited | T14: 02370 | U14: 344267938
A15: B | B15: R2 Rockland Weymouth/Union | C15: George T. Wilkinson | D15: Commercial HVAC service and mechanical contractor | E15: 405 VFW Dr, Ste 1 | F15: Rockland | G15: (781) 335-2622 | I15: Geoffrey Wilkinson (Chief Executive Officer) | J15: Dispatch, service software and field devices. Lead with help desk and device management. | K15: 68 | L15: 15840000 | M15: 1951 | O15: gtwilkinson.com | Q15: Not visited | T15: 02370 | U15: 48400778
A16: B | B16: R2 Rockland Weymouth/Union | C16: Commonwealth Building Systems | D16: Drywall and framing subcontractor | E16: 17 Rockview Way | F16: Rockland | G16: (781) 792-0032 | J16: Estimating and project files plus field crews. Lead with backup and email fraud protection. | K16: 60 | L16: 13390000 | M16: 2004 | O16: commonwealthbuildingsystems.com | P16: Next door to K5. Pair the stops. | Q16: Not visited | T16: 02370 | U16: 352266165
A17: B | B17: R2 Rockland Weymouth/Union | C17: Bendon Gear & Machine | D17: Precision gear and machine shop (defense work) | E17: 100 Weymouth St, Ste A1 | F17: Rockland | G17: (781) 878-8100 | I17: S. Belezos (Founder and Chief Executive Officer) | J17: Defense suppliers face CMMC requirements. Ask how they are handling CMMC and NIST 800-171. | K17: 25 | L17: 6443000 | M17: 1966 | O17: bendongear.com | P17: ITAR and CMMC pressure is a strong door opener for machine shops. | Q17: Not visited | T17: 02370 | U17: 7965364
A18: B | B18: R2 Rockland Weymouth/Union | C18: Alletess Medical Laboratory | D18: Clinical allergy and immunology lab | E18: 14 Howard St | F18: Rockland | G18: (800) 225-5404 | H18: John Connelly (IT Specialist) | I18: Mark McDonough (Chief Executive Officer) | J18: CLIA lab with PHI. Lead with HIPAA risk assessment and lab system uptime. | K18: 25 | L18: 7713000 | M18: 1980 | O18: foodallergy.com | Q18: Not visited | T18: 02370 | U18: 4066062
A19: C | B19: R2 Rockland Weymouth/Union | C19: Rockland Trust (Independent Bank Corp) | D19: Commercial bank, corporate offices | E19: 288 Union St | F19: Rockland | G19: (508) 732-7072 | H19: Dave Marsh (Interim Chief Information Officer) | J19: Enterprise bank with a full IT department. Networking and events only. | K19: 2294 | L19: 948692000 | M19: 1907 | N19: Independent Bank Corp | O19: rocklandtrust.com | P19: Long shot. Do not cold walk in. Useful for community sponsorship visibility. | Q19: Not visited | T19: 02370 | U19: 59785811
A20: C | B20: R2 Rockland Weymouth/Union | C20: United A/C, Heating & Refrigeration | D20: Commercial HVAC and refrigeration contractor | E20: 333 Weymouth St | F20: Rockland | G20: (781) 871-1060 | I20: Thomas Scolaro (President) | J20: Field techs on mobile devices and dispatch software. Lead with help desk and device management. | K20: 91 | L20: 2576000 | M20: 1985 | O20: united-hvac.com | P20: Employee count may include field crews. | Q20: Not visited | T20: 02370 | U20: 353591703
A21: C | B21: R2 Rockland Weymouth/Union | C21: Green Environmental | D21: Environmental testing and consulting | E21: 296 Weymouth St, Ste C | F21: Rockland | G21: (617) 479-0550 | I21: Donnie Green (President) | J21: Lab data and client reports need retention and backup. Lead with data protection. | K21: 30 | L21: 5078000 | M21: 1986 | O21: greenenvironmental.com | Q21: Not visited | T21: 02370 | U21: 29426949
A22: C | B22: R2 Rockland Weymouth/Union | C22: OneScience | D22: Scientific staffing and lab services | E22: 222 Weymouth St, Ste 2 | F22: Rockland | G22: (508) 930-1270 | J22: Placement records and client portals. Lead with M365 security and help desk. | K22: 30 | L22: 6242000 | M22: 1999 | O22: onescience.com | Q22: Not visited | T22: 02370 | U22: 50397914
A23: C | B23: R2 Rockland Weymouth/Union | C23: MIJA | D23: Pressure gauge and sensor manufacturer | E23: 11 Commerce Rd, Ste C | F23: Rockland | G23: (781) 871-5750 | I23: James Sommerio (President) | J23: Manufacturer with fire safety OEM customers. Lead with production uptime and email security. | K23: 29 | L23: 5180000 | M23: 1972 | N23: Valcom / Keltron | O23: mija.com | P23: Acquired by Keltron. Confirm who owns IT decisions locally. | Q23: Not visited | T23: 02370 | U23: 51856559
A24: C | B24: R2 Rockland Weymouth/Union | C24: RuggedMade | D24: Log splitters and outdoor power equipment, e-commerce | E24: 7 Market St | F24: Rockland | G24: (855) 878-4433 | I24: Jared Malarsky (President) | J24: E-commerce ops and warehouse systems. Lead with uptime and endpoint security. | K24: 24 | L24: 6200000 | M24: 2007 | O24: ruggedmade.com | Q24: Not visited | T24: 02370 | U24: 363680524
A25: A | B25: N1 Norwell Accord Park | C25: Avedis Zildjian Company | D25: Cymbal and drumstick maker, global HQ and factory | E25: 22 Longwater Dr | F25: Norwell | G25: (781) 871-2200 | H25: James Clifford (Senior Director, Information Technology) | I25: Thomas Young (Senior Vice President, Chief Financial Officer and Treasurer) | J25: 400 year old brand with modern e-commerce and a factory floor. Lead with plant uptime and security. | K25: 286 | L25: 32828000 | M25: 1929 | O25: zildjian.com | P25: Vic Firth is part of Zildjian, same campus. Iconic account for local proof. | Q25: Not visited | T25: 02061 | U25: 8996860
A26: A | B26: N1 Norwell Accord Park | C26: Radius Financial Group | D26: Mortgage lender, HQ | E26: 600 Longwater Dr, Ste 107 | F26: Norwell | G26: (877) 223-4800 | H26: Jake Gent (IT Support Specialist) | I26: David O'Connor (Chief Technology Officer) | J26: GLBA safeguards and loan file security. Lead with compliance, MDR and endpoint management. | K26: 281 | L26: 11835000 | M26: 1999 | O26: radiusgrp.com | P26: Same building as Miniter Group, different suite. Pair the stops. | Q26: Not visited | T26: 02061 | U26: 371618282
A27: A | B27: N1 Norwell Accord Park | C27: NVNA and Hospice (Norwell VNA) | D27: Visiting nurse association and hospice, nonprofit | E27: 120 Longwater Dr, Ste 104 | F27: Norwell | G27: (781) 659-2342 | H27: Samuel Lutz (It Help Desk Technician) | I27: Bj Snow (Chief Human Resources Officer) | J27: Clinicians in the field on mobile devices with PHI. Lead with HIPAA, device management and help desk. | K27: 262 | L27: 22797000 | M27: 1920 | O27: nvna.org | P27: Nonprofit budget cycle. EHR uptime and clinician onboarding speed are real pains. | Q27: Not visited | T27: 02061 | U27: 82658395
A28: A | B28: N1 Norwell Accord Park | C28: DIH Holding US (Hocoma) | D28: Rehab robotics and medtech, US HQ | E28: 77 Accord Park Dr, Ste D1 | F28: Norwell | G28: (617) 871-2101 | H28: Haile Mitiku (Manager, Information Technology) | I28: Jason Chen (Chief Executive Officer & Chairman) | J28: Public medtech company with FDA documentation needs. Lead with compliance ready IT and security. | K28: 200 | L28: 69573000 | M28: 2021 | O28: dih.com | P28: NASDAQ listed. Hocoma brand runs from same office. | Q28: Not visited | T28: 02061 | U28: 481121880
A29: A | B29: N1 Norwell Accord Park | C29: Miniter Group | D29: Lender placed insurance and insurtech | E29: 600 Longwater Dr, Ste 301 | F29: Norwell | G29: (800) 646-4837 | H29: Wayne Brantley (Chief Information Officer) | I29: Julianne Gilpin (President & Chief Executive Officer) | J29: Insurance data plus bank clients means audits. Lead with SOC 2 support and security posture. | K29: 120 | L29: 71702000 | M29: 1970 | O29: miniter.com | P29: Same building as Radius. Two ICP financial accounts in one stop. | Q29: Not visited | T29: 02061 | U29: 25117527
A30: A | B30: N1 Norwell Accord Park | C30: Snow & Jones | D30: Plumbing and HVAC wholesale distributor, HQ | E30: 85 Accord Park Dr | F30: Norwell | G30: (781) 878-3312 | I30: Danielle Jones (President) | J30: Multi branch distributor on one ERP. Lead with branch connectivity, uptime and ransomware defense. | K30: 90 | L30: 14844000 | M30: 1952 | O30: snowandjones.com | P30: 7 locations run from here. | Q30: Not visited | T30: 02061 | U30: 93767622
A31: A | B31: N1 Norwell Accord Park | C31: Airxchange | D31: Energy recovery ventilation components manufacturer | E31: 85 Longwater Dr | F31: Rockland | G31: (781) 871-4816 | I31: Randall Steele (President & Chief Executive Officer) | J31: OEM manufacturer with lean office staff. Lead with co-managed IT and production uptime. | K31: 70 | L31: 21533000 | M31: 1981 | O31: airxchange.com | P31: Rockland address but sits in the Accord Park corridor. Route with Norwell stops. | Q31: Not visited | T31: 02370 | U31: 2935868
A32: B | B32: N1 Norwell Accord Park | C32: Alternatives ABA | D32: ABA therapy provider | E32: 76 Accord Park Dr | F32: Norwell | G32: (781) 923-0900 | J32: Therapists documenting sessions on tablets. Lead with HIPAA, MDM and fast clinician onboarding. | K32: 199 | L32: 16725000 | M32: 2015 | O32: alternativesaba.com | P32: ABA groups grow fast and outgrow their IT. | Q32: Not visited | T32: 02061 | U32: 397516336
A33: B | B33: N1 Norwell Accord Park | C33: North River Home Care | D33: Private home care agency | E33: 275 Longwater Dr | F33: Norwell | G33: (781) 352-0939 | I33: Heather Kenney (Owner) | J33: Caregiver scheduling and PHI on personal devices. Lead with HIPAA and mobile device management. | K33: 146 | L33: 16932000 | M33: 1975 | O33: northriverhc.com | Q33: Not visited | T33: 02061 | U33: 347309462
A34: B | B34: N1 Norwell Accord Park | C34: Radio Solutions | D34: Two way radio and wireless communications dealer | E34: 55 Accord Park Dr | F34: Norwell | G34: (781) 561-3000 | H34: Matthew Dalton (Lead System Engineer) | I34: Admir Surkovic (President, Chief Executive Officer) | J34: Tech adjacent but not an MSP. Lead with M365, security and back office systems. | K34: 58 | L34: 12007000 | M34: 1998 | O34: radiosolutionsinc.com | P34: Possible referral partner too. They see every public safety and facilities buyer locally. | Q34: Not visited | T34: 02061 | U34: 354245370
A35: B | B35: N1 Norwell Accord Park | C35: TryAngle Foods | D35: Food distribution and provisions | E35: 17 Accord Park Dr, Ste 202 | F35: Norwell | G35: (781) 871-6969 | I35: Doug Vonlderstein (Founder) | J35: Orders, routing and invoicing systems. Lead with uptime and email fraud protection. | K35: 49 | L35: 9752000 | M35: 1977 | O35: tryanglefoods.com | Q35: Not visited | T35: 02061 | U35: 126845033
A36: B | B36: N1 Norwell Accord Park | C36: Blue Bear Plumbing, Heating & Air | D36: Residential home services, fast growing | E36: 300 Longwater Dr | F36: Norwell | G36: (781) 531-8227 | I36: Christopher Murphy (Owner) | J36: Fast growth home services firm. Lead with scaling help desk, dispatch uptime and onboarding techs. | K36: 34 | L36: 1166000 | M36: 2017 | O36: bluebearplumbing.com | P36: PE style growth playbook. Headcount likely higher than listed. | Q36: Not visited | T36: 02061 | U36: 451726485
A37: B | B37: N1 Norwell Accord Park | C37: The Driscoll Agency | D37: Specialty insurance agency | E37: 141 Longwater Dr, Ste 203 | F37: Norwell | G37: (781) 681-6656 | I37: Sean Driscoll (Owner) | J37: Client PII and carrier portals. Lead with email security and compliance basics. | K37: 23 | L37: 7217000 | M37: 1960 | O37: driscollagency.com | Q37: Not visited | T37: 02061 | U37: 41815502
A38: C | B38: N1 Norwell Accord Park | C38: Safety-Kleen (Clean Harbors) | D38: Environmental services, corporate offices | E38: 42 Longwater Dr | F38: Norwell | G38: (800) 323-5040 | H38: Caroline Johal (Group Manager, Information Technology Enterprise Solution) | J38: Clean Harbors corporate campus. Enterprise IT. Networking only. | K38: 4300 | L38: 1514886000 | M38: 1963 | N38: Clean Harbors | O38: safety-kleen.com | P38: Long shot. Skip on drop-off routes unless door is open. | Q38: Not visited | T38: 02061 | U38: 92389930
A39: C | B39: N1 Norwell Accord Park | C39: Sullivan Tire | D39: Tire and auto service chain, corporate HQ | E39: 41 Accord Park Dr | F39: Norwell | G39: (781) 982-1550 | H39: Joshua Sweeney (Supervisor, Application & Systems Development) | J39: Large internal IT exists. Pitch co-managed burst capacity or specific projects only. | K39: 1817 | L39: 242210000 | M39: 1955 | O39: sullivantire.com | P39: Family owned, HQ here. Worth relationship building even if no quick win. | Q39: Not visited | T39: 02061 | U39: 112869812
A40: C | B40: N1 Norwell Accord Park | C40: Signet Electronic Systems | D40: Low voltage systems integrator | E40: 90 Longwater Dr | F40: Norwell | G40: (781) 871-5888 | H40: William Ainslie (Healthcare Systems Engineer) | I40: Brad Caron (President) | J40: Integrator, now Pavion owned. Treat as partner or referral source more than prospect. | K40: 160 | L40: 59128000 | M40: 1974 | N40: Pavion | O40: signetgroup.net | P40: They install AV, security and nurse call. Complementary, not competing. Coffee meeting target. | Q40: Not visited | T40: 02061 | U40: 207552767
A41: A | B41: N2 Norwell Rt53/QueenAnne's | C41: South Shore Skin Center | D41: Dermatology practice and med spa | E41: 75 Washington St, Ste 1 | F41: Norwell | G41: (781) 878-6495 | J41: EHR uptime and HIPAA. Lead with a HIPAA security risk assessment, which insurers now expect. | K41: 86 | L41: 3100000 | M41: 1984 | O41: southshoreskincenter.com | P41: Multi provider practice. Visit mid afternoon, never during morning patient rush. | Q41: Not visited | T41: 02061 | U41: 227410374
A42: B | B42: N2 Norwell Rt53/QueenAnne's | C42: Jack Conway & Co. | D42: Real estate brokerage, HQ | E42: 137 Washington St | F42: Norwell | G42: (888) 735-3574 | I42: Al Becker (Real Estate President & Chief Operating Officer & Agent) | J42: 22 offices and hundreds of agents on shared systems. Lead with help desk and branch support. | K42: 700 | L42: 374260000 | M42: 1956 | O42: jackconway.com | P42: Employee figure includes agents. Corporate staff here is much smaller. | Q42: Not visited | T42: 02061 | U42: 17287496
A43: B | B43: N2 Norwell Rt53/QueenAnne's | C43: Southwood at Norwell Nursing Center | D43: Skilled nursing facility | E43: 501 Cordwainer Dr | F43: Norwell | G43: (781) 982-7450 | J43: EHR, nurse call and HIPAA on a 24x7 clock. Lead with reliable support and security. | K43: 124 | L43: 23544000 | M43: 1993 | O43: southwoodatnorwell.com | P43: Visit administrator midweek, mid morning. | Q43: Not visited | T43: 02061 | U43: 98615871
A44: B | B44: N2 Norwell Rt53/QueenAnne's | C44: Proven Behavior Solutions | D44: ABA therapy centers | E44: 80 Washington St, Ste Q57 | F44: Norwell | G44: (781) 290-3886 | I44: Kyle Bray (President & Chief Operating Officer) | J44: Growing multi site ABA group. Lead with HIPAA, MDM and opening new sites fast. | K44: 79 | L44: 2726000 | M44: 2015 | O44: provenaba.com | P44: Queen Anne's Corner plaza. Three targets share the 80 Washington St complex. | Q44: Not visited | T44: 02061 | U44: 397758004
A45: B | B45: N2 Norwell Rt53/QueenAnne's | C45: South Shore Autism Center | D45: ABA therapy centers | E45: 45 Pond St | F45: Norwell | G45: (781) 421-6182 | I45: Erin McLoughlin (Chief Executive Officer) | J45: Two growing clinic sites. Lead with HIPAA, Wi-Fi reliability and new hire device turnaround. | K45: 67 | L45: 14297000 | M45: 2016 | O45: ssautismcenter.com | Q45: Not visited | T45: 02061 | U45: 403845227
A46: B | B46: N2 Norwell Rt53/QueenAnne's | C46: LMHS, P.C. | D46: CPA firm | E46: 80 Washington St, Bldg S | F46: Norwell | G46: (781) 878-9111 | H46: Randy Toscano (Director, System and Business Partner) | J46: FTC Safeguards requires CPA firms to maintain a written security plan. Ask who owns theirs. | K46: 35 | L46: 5895000 | M46: 1987 | O46: lmhspc.com | P46: Same plaza as Proven Behavior and Oral Surgery South. | Q46: Not visited | T46: 02061 | U46: 348042852
A47: B | B47: N2 Norwell Rt53/QueenAnne's | C47: Oral Surgery South | D47: Oral and maxillofacial surgery practice | E47: 80 Washington St, Ste N51 | F47: Norwell | G47: (781) 871-1677 | I47: Tony Rubeiz (Partner) | J47: Imaging systems and PHI across four sites. Lead with HIPAA and practice uptime. | K47: 23 | L47: 4972000 | M47: 1981 | O47: oralsurgerysouth.com | P47: 4 locations. Same plaza as LMHS and Proven Behavior. | Q47: Not visited | T47: 02061 | U47: 1122062802
A48: C | B48: N2 Norwell Rt53/QueenAnne's | C48: Arbour Counseling Services | D48: Behavioral health clinics | E48: 384 Washington St, Ste 202 | F48: Norwell | G48: (781) 871-6550 | H48: Jose Torres (IT Specialist & IT Engineer & Senior Manager & Director, ...) | J48: UHS corporate IT covers them. Skip unless a local contact invites the conversation. | K48: 403 | L48: 11440000 | M48: 1994 | N48: Universal Health Services | O48: arbourhealth.com | P48: Branch of a national system. | Q48: Not visited | T48: 02061 | U48: 2556714
A49: C | B49: N2 Norwell Rt53/QueenAnne's | C49: Friendship Home | D49: Nonprofit respite and disability services | E49: 458 Main St | F49: Norwell | G49: (781) 659-8202 | I49: Wilma Goodhue (Co-Founder) | J49: Lean nonprofit. Lead with right sized support and donor data protection. | K49: 64 | L49: 7935000 | M49: 1999 | O49: friendshiphome.net | Q49: Not visited | T49: 02061 | U49: 348228861
A50: C | B50: N2 Norwell Rt53/QueenAnne's | C50: Dolomite Bio (Blacktrace US) | D50: Single cell biology instruments, US office | E50: 156 Norwell Ave | F50: Norwell | G50: +44 1763 252149 | J50: Life sciences instruments office. Lead with lab IT support for US operations. | K50: 63 | L50: 15013000 | M50: 2016 | N50: Blacktrace Holdings (UK) | O50: dolomite-bio.com | P50: Verify before visiting. US office is small and phone routes to UK. | Q50: Not visited | T50: 02061 | U50: 395765368
A51: C | B51: N2 Norwell Rt53/QueenAnne's | C51: AJAX Jets | D51: Private jet charter | E51: 167 Washington St | F51: Norwell | G51: (617) 855-5378 | J51: High net worth client data and scheduling ops. Lead with security and white glove support. | K51: 32 | L51: 6756000 | O51: ajaxjets.com | Q51: Not visited | T51: 02061 | U51: 541625269
A52: A | B52: H1 Hanover Rt53/139 | C52: Cardinal Cushing Centers | D52: Special education and disability services nonprofit | E52: 405 Washington St | F52: Hanover | G52: (781) 826-6371 | H52: Evan Moniz (Manager, Network) | I52: Gina Rosas (Chief Operating Officer) | J52: Student records, HIPAA and FERPA with a lean budget. Lead with co-managed support and security. | K52: 410 | L52: 24761000 | M52: 1947 | O52: cushingcenters.org | P52: Large campus on Rt 53. Ask for the business office. | Q52: Not visited | T52: 02339 | U52: 30739950
A53: A | B53: H1 Hanover Rt53/139 | C53: Homestead Mortgage | D53: Mortgage lender | E53: 427 Columbia Rd, Ste 114 | F53: Hanover | G53: (781) 924-5482 | I53: Kimmie Miller (Owner) | J53: GLBA safeguards and loan officer laptops everywhere. Lead with compliance and device management. | K53: 82 | L53: 5328000 | M53: 2008 | O53: myhomesteadmortgage.com | P53: Same building as Merrill Associates. | Q53: Not visited | T53: 02339 | U53: 344599909
A54: B | B54: H1 Hanover Rt53/139 | C54: First Resource Management | D54: Affordable housing property management | E54: 2001 Washington St | F54: Hanover | G54: (781) 659-0025 | I54: Gordon Pulsifer (President) | J54: HUD compliance paperwork and resident data across sites. Lead with secure, supported systems. | K54: 55 | L54: 14197000 | M54: 1985 | O54: firstresourcecompanies.com | P54: Across the street from Jannell Ford. | Q54: Not visited | T54: 02339 | U54: 359188055
A55: B | B55: H1 Hanover Rt53/139 | C55: Wozny/Barbar & Associates | D55: MEP engineering firm | E55: 1076 Washington St | F55: Hanover | G55: (781) 826-4144 | I55: Zbigniew Wozny (President) | J55: Revit and CAD workstations. Lead with performance, backup and project deadlines. | K55: 34 | L55: 6880000 | M55: 1988 | O55: wbaengineers.com | Q55: Not visited | T55: 02339 | U55: 353985624
A56: B | B56: H1 Hanover Rt53/139 | C56: Merrill Associates | D56: Civil engineering and land surveying | E56: 427 Columbia Rd | F56: Hanover | G56: (781) 826-9200 | I56: Robert Merrill (President) | J56: Survey data and CAD files. Lead with backup and file access speed. | K56: 27 | L56: 1517000 | O56: merrillinc.com | P56: Same building as Homestead Mortgage. Pair the stops. | Q56: Not visited | T56: 02339 | U56: 343333439
A57: C | B57: H1 Hanover Rt53/139 | C57: McGee Toyota of Hanover | D57: Toyota dealership, McGee Automotive Family flagship | E57: 860 Washington St | F57: Hanover | G57: (781) 829-0343 | J57: FTC Safeguards Rule applies to dealers. Ask who runs their safeguards program. | K57: 701 | L57: 19784000 | M57: 1974 | N57: McGee Automotive Family | O57: mcgeetoyota.com | P57: Group wide employee count. Group may centralize IT. GM can still open the door. | Q57: Not visited | T57: 02339 | U57: 56511689
A58: C | B58: H1 Hanover Rt53/139 | C58: Planet Subaru | D58: Independent Subaru dealership | E58: 596 Washington St | F58: Hanover | G58: (781) 826-4444 | I58: Marcel Choiniere (General Manager, Fixed Operations) | J58: Independent dealer subject to FTC Safeguards. Lead with a safeguards gap review. | K58: 71 | L58: 18870000 | M58: 1998 | O58: planetsubaru.com | P58: Independently owned, decision maker on site. Best dealer target on the list. | Q58: Not visited | T58: 02339 | U58: 76400508
A59: C | B59: H1 Hanover Rt53/139 | C59: Jannell Ford | D59: Independent Ford dealership | E59: 2000 Washington St | F59: Hanover | G59: (781) 982-4500 | I59: Joseph Clapp (Owner) | J59: Family owned dealer. FTC Safeguards and DMS uptime are the openers. | K59: 21 | L59: 13683000 | M59: 1921 | O59: jannellford.com | P59: Employee count understated. Real headcount likely 80 plus. | Q59: Not visited | T59: 02339 | U59: 1128547688
A60: A | B60: H2 West Hanover industrial | C60: P.A. Landers | D60: Site development and paving contractor, HQ | E60: 351 Winter St | F60: Hanover | G60: (781) 826-8818 | H60: Anthony Emma (Director, Information Technology) | I60: Joseph Durant (Chief Operating Officer) | J60: Big contractor, prime wire fraud target. Lead with email security and estimating uptime. | K60: 280 | L60: 66695000 | M60: 1978 | O60: palanders.com | P60: One of the biggest private employers based in Hanover. | Q60: Not visited | T60: 02339 | U60: 80937600
A61: A | B61: H2 West Hanover industrial | C61: Buckley Associates | D61: HVAC equipment distributor and rep, HQ | E61: 385 King St | F61: Hanover | G61: (781) 878-5000 | H61: Devin Melo (Manager, Information Technology) | I61: Robert Buckley (Founder) | J61: 12 locations and near 100M revenue on one ERP. Lead with uptime, security and branch support. | K61: 135 | L61: 99989000 | M61: 1970 | O61: buckleyonline.com | P61: Biggest revenue target in Hanover on this list. | Q61: Not visited | T61: 02339 | U61: 16239075
A62: A | B62: H2 West Hanover industrial | C62: SRC Medical | D62: Medical device components manufacturer | E62: 263 Winter St | F62: Hanover | G62: (781) 826-9100 | H62: Lisa Raasch (Chief Information Officer) | I62: Roy Tinkham (President) | J62: FDA documentation and quality systems. Lead with compliance ready IT and uptime. | K62: 102 | L62: 18379000 | M62: 1972 | O62: srcmedical.com | P62: Medical manufacturing is a priority vertical. | Q62: Not visited | T62: 02339 | U62: 193593434
A63: A | B63: H2 West Hanover industrial | C63: Hapco | D63: Epoxy and urethane polymer manufacturer | E63: 353 Circuit St | F63: Hanover | G63: (781) 826-8801 | H63: Daniel McClelland (System Administrator) | I63: Fred DeSimone (General Manager) | J63: Formulations IP and production systems. Lead with security and backup. | K63: 76 | L63: 18177000 | M63: 1969 | O63: hapcoincorporated.com | P63: Phone corrected from web. ZoomInfo listed an out of state number. | Q63: Not visited | T63: 02339 | U63: 50678002
A64: A | B64: H2 West Hanover industrial | C64: Gem Gravure | D64: Wire marking inks and printing systems, HQ | E64: 112 School St | F64: Hanover | G64: (781) 878-0456 | H64: Matt Phung (IT Administrator) | I64: Joseph Gemelli (Founder) | J64: Third generation manufacturer with global customers. Lead with security and production uptime. | K64: 73 | L64: 18507000 | M64: 1952 | O64: gemgravure.com | P64: West Hanover village, near Circuit St loop. | Q64: Not visited | T64: 02339 | U64: 352771180
A65: A | B65: H2 West Hanover industrial | C65: Cri-Tech (Daikin) | D65: Specialty rubber compounds manufacturer | E65: 85 Winter St | F65: Hanover | G65: (781) 826-5600 | H65: Richard Park (Manager, Business Systems) | J65: Daikin owned but locally run plant. Lead with co-managed support for site systems. | K65: 54 | L65: 6341000 | M65: 1977 | N65: Daikin Industries | O65: critechinc.com | P65: Corporate IT may exist at Daikin America. Local plant manager still feels the pain. | Q65: Not visited | T65: 02339 | U65: 32690370
A66: B | B66: H2 West Hanover industrial | C66: A. Murphy Inc | D66: Site work and utility contractor | E66: 35 Hanover St | F66: Hanover | G66: (781) 826-0222 | I66: Michael Murphy (Owner and Operator) | J66: Field crews and office estimating. Lead with email fraud protection and file backup. | K66: 127 | L66: 12799000 | M66: 1980 | O66: amurphy.com | Q66: Not visited | T66: 02339 | U66: 6295262
A67: B | B67: H2 West Hanover industrial | C67: Eyesaver International | D67: Safety eyewear manufacturer | E67: 348 Circuit St, Ste 2 | F67: Hanover | G67: (781) 829-0808 | I67: Stephen George (President) | J67: Product and order systems. Lead with M365 and endpoint management. | K67: 42 | L67: 8590000 | M67: 1990 | O67: eyesaverinternational.com | P67: Same building as Sturtevant. Pair the stops. | Q67: Not visited | T67: 02339 | U67: 43125676
A68: B | B68: H2 West Hanover industrial | C68: Sturtevant | D68: Micronizing and powder processing equipment | E68: 348 Circuit St, Ste 1 | F68: Hanover | G68: (781) 829-6501 | I68: Sturt English (President & Chief Executive Officer) | J68: 140 year old machine builder. Lead with modernizing office IT without disrupting the shop. | K68: 36 | L68: 4909000 | M68: 1883 | O68: sturtevantinc.com | P68: Same building as Eyesaver International. | Q68: Not visited | T68: 02339 | U68: 92094650
A69: B | B69: H2 West Hanover industrial | C69: Lubrite Technologies | D69: Self lubricating bearings manufacturer | E69: 145 Webster St, Ste J | F69: Hanover | G69: (781) 871-1420 | J69: Engineering drawings and customer specs. Lead with backup and secure file sharing. | K69: 28 | L69: 9315000 | M69: 2011 | O69: lubritetechnologies.com | Q69: Not visited | T69: 02339 | U69: 122486882
A70: C | B70: H2 West Hanover industrial | C70: South Shore YMCA (Emilson Branch / Admin) | D70: Nonprofit YMCA association | E70: 75 Mill St | F70: Hanover | G70: (781) 829-8585 | J70: Multi branch nonprofit with member data and childcare compliance. Lead with co-managed support. | K70: 1262 | L70: 36226000 | O70: ssymca.org | P70: Employee count spans all branches and seasonal camp staff. | Q70: Not visited | T70: 02339 | U70: 35750136
A71: C | B71: H2 West Hanover industrial | C71: Hingham Moving Services | D71: Moving and storage company | E71: 285 Circuit St | F71: Hanover | G71: (617) 319-7027 | J71: Scheduling, dispatch and customer data. Lead with simple reliable IT and phones. | K71: 72 | L71: 3145000 | M71: 1982 | O71: hinghammoving.com | Q71: Not visited | T71: 02339 | U71: 405942027
A72: C | B72: H2 West Hanover industrial | C72: Burgopak USA | D72: Packaging design firm, US office | E72: 24 Rockland St, Ste 5 | F72: Hanover | G72: +44 20 7089 1950 | J72: Small US office of a UK firm. Lead with being their local IT presence. | K72: 30 | L72: 8271000 | N72: Burgopak (UK) | O72: burgopak.com | P72: Verify before visiting. Phone routes to UK. | Q72: Not visited | T72: 02339 | U72: 11619277
A73: A | B73: P1 Pembroke corporate parks | C73: Royal Health Group | D73: Family owned nursing home group, HQ | E73: 42 Winter St | F73: Pembroke | G73: (781) 826-2393 | H73: Jimmy Noel (Manager, Information Technology) | I73: Pamela Jones (Chief Financial Officer) | J73: 12 facilities of EHR, nurse call and HIPAA. Lead with multi site support and security. | K73: 755 | L73: 34941000 | M73: 1998 | O73: royalhealthgroup.com | P73: HQ decides for all facilities. Employee count spans the group. | Q73: Not visited | T73: 02359 | U73: 44024049
A74: A | B74: P1 Pembroke corporate parks | C74: FMC Ice Sports | D74: Ice rink management company, HQ | E74: 100 Schoosett St, Bldg 3 | F74: Pembroke | G74: (888) 747-5283 | J74: 25 rinks on POS, scheduling and payment systems. Lead with multi site support and uptime. | K74: 226 | L74: 54426000 | M74: 1992 | O74: fmcicesports.com | P74: HQ office decides for all sites. Strong multi site play. | Q74: Not visited | T74: 02359 | U74: 40865749
A75: A | B75: P1 Pembroke corporate parks | C75: Thayer Scale | D75: Industrial weighing and feeding equipment, HQ | E75: 91 Schoosett St | F75: Pembroke | G75: (855) 784-2937 | H75: Chris Geer (Information Technology Consultant) | I75: Frank Hyer (Chairman & Chief Executive Officer) | J75: Engineering IP and global customers. Lead with security, backup and shop floor uptime. | K75: 82 | L75: 23837000 | M75: 1949 | O75: thayerscale.com | P75: Classic ICP manufacturer. | Q75: Not visited | T75: 02359 | U75: 38076611
A76: A | B76: P1 Pembroke corporate parks | C76: Nelco Products | D76: Cable ties and wire management, distribution HQ | E76: 22 Riverside Dr | F76: Pembroke | G76: (800) 346-3526 | H76: Patrick Wong (Director, Information Technology & Materials) | I76: Miriam Nelson (Owner) | J76: E-commerce and warehouse ops. Lead with uptime, EDI reliability and security. | K76: 81 | L76: 37741000 | M76: 1984 | O76: nelcoproducts.com | Q76: Not visited | T76: 02359 | U76: 71779517
A77: B | B77: P1 Pembroke corporate parks | C77: New England Village | D77: Nonprofit for adults with disabilities | E77: 664 School St | F77: Pembroke | G77: (781) 293-5461 | H77: Tim McKinney (Manager, Information Technology) | I77: Christine Chagnon (President & Chief Executive Officer) | J77: Resident records and lean budgets. Lead with right sized managed IT and HIPAA. | K77: 166 | L77: 5359000 | M77: 1972 | O77: newenglandvillage.org | Q77: Not visited | T77: 02359 | U77: 27394913
A78: B | B78: P1 Pembroke corporate parks | C78: Preferred Mechanical Services | D78: Mechanical contractor | E78: 223 Center St | F78: Pembroke | G78: (781) 293-1200 | I78: Jennifer Meade (Founder) | J78: Field techs and service contracts. Lead with dependable help desk and dispatch uptime. | K78: 77 | L78: 3960000 | M78: 1992 | O78: preferredmechanicalservices.com | Q78: Not visited | T78: 02359 | U78: 345994045
A79: B | B79: P1 Pembroke corporate parks | C79: Your Electrical Solution | D79: Electrical contractor | E79: 345 Washington St | F79: Pembroke | G79: (781) 331-3500 | H79: Peter Ockerbloom (Telecom Systems Technician) | I79: Bruce Sylvester (Owner) | J79: Growing contractor. Lead with email fraud protection and field device support. | K79: 76 | L79: 23819000 | M79: 1996 | O79: yourelectricalsolutions.com | Q79: Not visited | T79: 02359 | U79: 450765740
A80: B | B80: P1 Pembroke corporate parks | C80: Revenue Solutions (RSI) | D80: Government tax software company | E80: 42 Winter St, Ste 36 | F80: Pembroke | G80: (781) 826-1546 | H80: Jonathan Epstein (Director, Information Technology) | I80: Blake Ramsey (President) | J80: Software firm with government clients and audits. Lead with co-managed security and helpdesk. | K80: 61 | L80: 4335000 | M80: 1996 | O80: rsidelivers.com | P80: Same complex as Royal Health Group. Pair the stops. | Q80: Not visited | T80: 02359 | U80: 122601758
A81: B | B81: P1 Pembroke corporate parks | C81: Acella Construction | D81: Commercial general contractor | E81: 38 Washington St | F81: Pembroke | G81: (781) 681-9240 | I81: Saul Schrader (President) | J81: 50M GC with project data everywhere. Lead with email fraud protection and Procore uptime. | K81: 42 | L81: 52519000 | M81: 2003 | O81: acellaconstruction.com | P81: Builds for healthcare and schools locally. Referral rich. | Q81: Not visited | T81: 02359 | U81: 722847
A82: B | B82: P1 Pembroke corporate parks | C82: Ritchie Navigation | D82: Marine compass manufacturer since 1850 | E82: 243 Oak St | F82: Pembroke | G82: (781) 826-5131 | I82: Jonathan Sherman (President) | J82: Storied manufacturer. Lead with modern security wrapped around legacy systems. | K82: 41 | L82: 8845000 | M82: 1850 | O82: ritchienavigation.com | P82: America's oldest compass maker. Great conversation starter. | Q82: Not visited | T82: 02359 | U82: 87149342
A83: B | B83: P1 Pembroke corporate parks | C83: Protectowire FireSystems | D83: Linear heat detection manufacturer, HQ | E83: 60 Washington St | F83: Pembroke | G83: (781) 826-3878 | H83: Michael Hall (System Engineer) | I83: Gerald Holmes (Founder) | J83: Global OEM with engineering IP. Lead with security and dependable office IT. | K83: 31 | L83: 18925000 | M83: 1938 | O83: protectowire.com | Q83: Not visited | T83: 02359 | U83: 64980067
A84: B | B84: P1 Pembroke corporate parks | C84: FCI Ophthalmics | D84: Ophthalmic surgical devices, US office | E84: 30 Corporate Park Dr, Ste 310 | F84: Pembroke | G84: (800) 932-4202 | J84: FDA regulated device distribution. Lead with compliance ready IT for a lean office. | K84: 22 | L84: 3532000 | M84: 1984 | N84: FCI (France) | O84: fci-ophthalmics.com | Q84: Not visited | T84: 02359 | U84: 14041218
A85: C | B85: P1 Pembroke corporate parks | C85: Entegee / The Engineering Department | D85: Engineering staffing, national HQ (Adecco Group) | E85: 33 Riverside Dr | F85: Pembroke | G85: (877) 606-8765 | J85: Adecco corporate IT covers them. Networking value with branch leadership only. | K85: 346 | L85: 239291000 | M85: 1978 | N85: Adecco Group | O85: entegee.com | P85: The Engineering Department brand shares this building. | Q85: Not visited | T85: 02359 | U85: 38800308
A86: C | B86: P1 Pembroke corporate parks | C86: Horner Millwork | D86: Millwork and building products, Pembroke branch | E86: 55 Corporate Park Dr, Ste 1 | F86: Pembroke | G86: (781) 826-7770 | J86: Branch of Somerset HQ company. Local relationship can open the corporate door. | K86: 165 | L86: 16673000 | M86: 2001 | N86: North Atlantic Corp | O86: hornermillwork.com | P86: IT likely decided at North Atlantic Corp. | Q86: Not visited | T86: 02359 | U86: 31983788
A87: C | B87: P1 Pembroke corporate parks | C87: Markings Inc | D87: Pavement marking contractor | E87: 30 Riverside Dr | F87: Pembroke | G87: (781) 826-5171 | I87: Monique Souza (Owner) | J87: Seasonal field crews and bids. Lead with simple managed IT and email security. | K87: 42 | L87: 10558000 | M87: 1967 | O87: markingsinc.com | Q87: Not visited | T87: 02359 | U87: 354855362
A88: C | B88: P1 Pembroke corporate parks | C88: Peak Mechanical Services | D88: Commercial HVAC and plumbing contractor | E88: 35 Corporate Park Dr, Ste 2 | F88: Pembroke | G88: (781) 924-5982 | I88: Mario DiMartino (President) | J88: Dispatch and service software. Lead with help desk for field techs. | K88: 38 | L88: 16640000 | M88: 2007 | O88: peakmechanicalservices.com | Q88: Not visited | T88: 02359 | U88: 357482820
A89: C | B89: P1 Pembroke corporate parks | C89: Charm Medical Supply | D89: Home medical supplies (DME) | E89: 33 Riverside Dr, Ste 200 | F89: Pembroke | G89: (781) 829-9813 | I89: Wayne Saville (Chief Financial Officer) | J89: Medicaid billing and PHI. Lead with HIPAA and dependable order systems. | K89: 25 | L89: 4422000 | M89: 2000 | O89: charmmedical.com | P89: Same building as Entegee. | Q89: Not visited | T89: 02359 | U89: 12354801
A90: C | B90: P1 Pembroke corporate parks | C90: Cadete Enterprises | D90: Multi unit Dunkin' franchisee office | E90: 12 Riverside Dr | F90: Pembroke | G90: (781) 829-1156 | I90: Eric Eskander (Chief Executive Officer) | J90: Dozens of stores on POS and payroll systems. Lead with store uptime and PCI basics. | K90: 25 | L90: 4932000 | M90: 2000 | O90: cadeteenterprises.com | P90: Office staff small. Store count is the real footprint. | Q90: Not visited | T90: 02359 | U90: 379382675
A91: C | B91: P1 Pembroke corporate parks | C91: JLC Tech | D91: Architectural LED lighting manufacturer | E91: 370 Corporate Park Dr | F91: Pembroke | G91: (781) 826-8162 | I91: Mia Antonia (Principal Partner - Chief Financial Officer) | J91: Design files and order systems. Lead with backup and M365 security. | K91: 21 | L91: 4064000 | M91: 2010 | O91: jlc-tech.com | Q91: Not visited | T91: 02359 | U91: 355384049
A92: A | B92: W1 Whitman/Abington/Hanson | C92: T&K Asphalt Services | D92: Commercial paving contractor, HQ | E92: 7 Industrial Way | F92: Whitman | G92: (781) 826-3138 | I92: Peter Cleary (Chief Financial Officer) | J92: 80M contractor and a top wire fraud target. Lead with email security and estimating uptime. | K92: 125 | L92: 79566000 | M92: 1987 | O92: tkasphalt.com | P92: One of the largest paving firms in New England. | Q92: Not visited | T92: 02382 | U92: 184991889
A93: A | B93: W1 Whitman/Abington/Hanson | C93: Cape Cod Lumber | D93: Independent lumber yard and building products | E93: 225 Groveland St | F93: Abington | G93: (781) 878-0715 | I93: Thomas McManus (President) | J93: POS, inventory and delivery ops on one system. Lead with uptime and ransomware defense. | K93: 98 | L93: 27457000 | M93: 1958 | O93: capecodlumber.com | P93: Family owned. Decision makers on site. | Q93: Not visited | T93: 02351 | U93: 20517658
A94: B | B94: W1 Whitman/Abington/Hanson | C94: Southeastern ABA | D94: ABA therapy provider | E94: 116 Helen Dr | F94: Hanson | G94: (781) 924-1408 | J94: Fast growing therapy group. Lead with HIPAA, MDM and clinician onboarding speed. | K94: 153 | L94: 30140000 | M94: 2014 | O94: southeasternaba.com | Q94: Not visited | T94: 02341 | U94: 481093210
A95: B | B95: W1 Whitman/Abington/Hanson | C95: Sullivan's Inc | D95: Powersports accessories wholesale distributor | E95: 121 Franklin St | F95: Hanson | G95: (781) 293-9711 | I95: Bobby Sullivan (Owner and Operator) | J95: National distribution on EDI and warehouse systems. Lead with uptime and security. | K95: 141 | L95: 11685000 | O95: sullivansusa.com | P95: Family owned since 1948 era roots. Verified via web. | Q95: Not visited | T95: 02341 | U95: 371652590
A96: B | B96: W1 Whitman/Abington/Hanson | C96: Seoane Landscape Design | D96: Commercial landscape design and construction | E96: 551 Bedford St | F96: Abington | G96: (781) 878-1306 | I96: Louis Seoane (President, Operations & Sales) | J96: Crews, scheduling and billing. Lead with simple managed IT that keeps trucks rolling. | K96: 108 | L96: 22537000 | M96: 1972 | O96: seoanelandscape.com | Q96: Not visited | T96: 02351 | U96: 55133071
A97: B | B97: W1 Whitman/Abington/Hanson | C97: Whitman Company | D97: Metal finishing and plating | E97: 356 South Ave | F97: Whitman | G97: (781) 447-2422 | I97: William Whitman (President) | J97: Plating lines and quality certs. Lead with production uptime and simple secure IT. | K97: 100 | L97: 17480000 | M97: 1894 | O97: whitman-company.com | P97: Address confirmed via web. ZoomInfo listing was incomplete. | Q97: Not visited | T97: 02382 | U97: 128385304
A98: B | B98: W1 Whitman/Abington/Hanson | C98: Defense Investigators Group | D98: Insurance defense investigations | E98: PO Box 119 (call ahead) | F98: Hanson | G98: (800) 233-0417 | I98: Don Anderson (Owner) | J98: Sensitive case files and field investigators. Lead with security and secure remote access. | K98: 91 | L98: 16655000 | M98: 1990 | O98: defenseinvestigatorsgroup.com | P98: Street address not published. Call before attempting a visit. | Q98: Not visited | T98: 02341 | U98: 1160266888
A99: B | B99: W1 Whitman/Abington/Hanson | C99: Walsh Mechanical Contractors | D99: Mechanical contractor since 1918 | E99: 380 North Ave | F99: Abington | G99: (781) 871-7496 | J99: Century old contractor. Lead with email fraud protection and dependable office IT. | K99: 70 | L99: 25018000 | M99: 1918 | O99: walshmechanical.com | Q99: Not visited | T99: 02351 | U99: 74531004
A100: B | B100: W1 Whitman/Abington/Hanson | C100: Webster Printing | D100: Commercial printing | E100: 1069 W Washington St | F100: Hanson | G100: (781) 447-5484 | I100: Ernest Foster (President & Chief Executive Officer) | J100: Prepress files and tight deadlines. Lead with backup and workstation reliability. | K100: 50 | L100: 6726000 | M100: 1956 | O100: websterprinting.com | Q100: Not visited | T100: 02341 | U100: 353908367
...

Sheet Routes
A1: Drive routes
A2: Each route is a half day: 8 to 12 stops, one geography, no backtracking. Filter the Target List by the Route column, print it, go.
A4: Code | B4: Route | C4: Stops | D4: Tier A | E4: How to work it
A5: R1 | B5: Rockland: Exit 14 corridor (Hingham St, Ledgewood Pl, Reservoir Park) | C5: =COUNTIF('Target List'!$B$2:$B$105,"R1 *") -> 7 | D5: =COUNTIFS('Target List'!$B$2:$B$105,"R1 *",'Target List'!$A$2:$A$105,"A") -> 2 | E5: One exit, one loop. Start at Cutter, work the Ledgewood Pl buildings (three targets share them), end at FINTRX. EMD Serono is a drive-by; do not cold walk past security.
A6: R2 | B6: Rockland: Weymouth St / VFW Dr industrial + Union St center | C6: =COUNTIF('Target List'!$B$2:$B$105,"R2 *") -> 16 | D6: =COUNTIFS('Target List'!$B$2:$B$105,"R2 *",'Target List'!$A$2:$A$105,"A") -> 5 | E6: Best density on the list. Industrial loop first (Weymouth St, Commerce Rd, Rockview Way pairs), then Union St for the credit union. Morning route.
A7: N1 | B7: Norwell: Accord Park & Longwater Dr (Assinippi) | C7: =COUNTIF('Target List'!$B$2:$B$105,"N1 *") -> 16 | D7: =COUNTIFS('Target List'!$B$2:$B$105,"N1 *",'Target List'!$A$2:$A$105,"A") -> 7 | E7: Two connected office parks, walkable pairs everywhere. 600 Longwater alone holds Radius and Miniter. Zildjian and Snow & Jones anchor it.
A8: N2 | B8: Norwell: Rt 53 & Queen Anne's Corner (Washington St, Pond St) | C8: =COUNTIF('Target List'!$B$2:$B$105,"N2 *") -> 11 | D8: =COUNTIFS('Target List'!$B$2:$B$105,"N2 *",'Target List'!$A$2:$A$105,"A") -> 1 | E8: Straight run down Rt 53. The 80 Washington St plaza holds three targets in one parking lot. Afternoon route, clinics after 1:30.
A9: H1 | B9: Hanover: Rt 53 & Rt 139 (Washington St, Columbia Rd) | C9: =COUNTIF('Target List'!$B$2:$B$105,"H1 *") -> 8 | D9: =COUNTIFS('Target List'!$B$2:$B$105,"H1 *",'Target List'!$A$2:$A$105,"A") -> 2 | E9: Dealer row plus Cardinal Cushing campus. Jannell Ford and First Resource face each other; Homestead and Merrill share 427 Columbia Rd.
A10: H2 | B10: West Hanover industrial (Winter St, Circuit St, King St) | C10: =COUNTIF('Target List'!$B$2:$B$105,"H2 *") -> 13 | D10: =COUNTIFS('Target List'!$B$2:$B$105,"H2 *",'Target List'!$A$2:$A$105,"A") -> 6 | E10: Manufacturer heavy, go in the morning. Winter St first (Landers, SRC, Cri-Tech), then the Circuit St loop where Sturtevant and Eyesaver share a building.
A11: P1 | B11: Pembroke: Corporate Park, Riverside Dr, Schoosett St (Rt 139/53) | C11: =COUNTIF('Target List'!$B$2:$B$105,"P1 *") -> 19 | D11: =COUNTIFS('Target List'!$B$2:$B$105,"P1 *",'Target List'!$A$2:$A$105,"A") -> 4 | E11: Biggest route, split it in two if needed. Riverside Dr and Corporate Park Dr are back to back. Royal Health and RSI share 42 Winter St.
A12: W1 | B12: Whitman, Abington & Hanson | C12: =COUNTIF('Target List'!$B$2:$B$105,"W1 *") -> 13 | D12: =COUNTIFS('Target List'!$B$2:$B$105,"W1 *",'Target List'!$A$2:$A$105,"A") -> 2 | E12: Three towns, one arc. Pair the Franklin St stops in Hanson (Sullivan's, President Titanium). Call Defense Investigators before trying to visit.
A13: X1 | B13: Nearby, verify first | C13: =COUNTIF('Target List'!$B$2:$B$105,"X1 *") -> 1 | D13: =COUNTIFS('Target List'!$B$2:$B$105,"X1 *",'Target List'!$A$2:$A$105,"A") -> 0 | E13: Bay State PT HQ is in Braintree now. Call ahead, combine with a Rt 3 errand.
B15: Suggested first outing: N1 Norwell Accord Park. Highest tier A density, everything within a half mile, and Zildjian makes a story you can tell at every other door.

Sheet Drop-Off Playbook
B1: The Drop-Off Playbook
B2: You are not selling at the door. You are earning a name, a face, and permission to follow up.
B3: Every stop ends in one of three wins: two minutes with a decision maker, the decision maker's name and email from the front desk, or a warm reason to come back. Anything else is a skip, not a failure.
B5: Before you leave
B6: • Pick one route from the Routes tab and work it end to end. 8 to 12 stops fits a half day.
B7: • Print a packet per stop: one page flyer, business card, handwritten sticky note. Folder, not a box.
B8: • Match the flyer to the stop. Experts On Demand where an IT contact is listed. Managed services or the Zero-Touch device page everywhere else.
B9: • Google each company that morning. Ten seconds per stop confirms they still exist and saves a wasted drive.
B10: • Check the IT contact and Owner columns before walking in. Asking for a person by name changes the whole interaction.
B12: Timing
B13: • Tuesday through Thursday. Monday is chaos, Friday is checkout.
B14: • Manufacturers and contractors: 8:30 to 11:00. Owners are in early.
... B63: • Contact names came from a database. Confirm at the desk: asking whether [name] still runs IT is itself a fine opener.
